dtcc_model/__init__.py
dtcc_model/building.py
dtcc_model/city.py
dtcc_model/dtcc_pb2.py
dtcc_model/geometry.py
dtcc_model/grid.py
dtcc_model/gridfields.py
dtcc_model/landuse.py
dtcc_model/logging.py
dtcc_model/meshes.py
dtcc_model/meshfields.py
dtcc_model/model.py
dtcc_model/pointcloud.py
dtcc_model/raster.py
dtcc_model/roadnetwork.py
dtcc_model/utils.py
dtcc_model-0.7.21.dist-info/LICENSE
dtcc_model-0.7.21.dist-info/METADATA
dtcc_model-0.7.21.dist-info/WHEEL
dtcc_model-0.7.21.dist-info/top_level.txt
dtcc_model-0.7.21.dist-info/RECORD
