Metadata-Version: 2.1
Name: dtcc-model
Version: 0.7.21
Summary: DTCC Model
Author-email: Anders Logg <logg@chalmers.se>, Vasilis Naserentin <vasilis.naserentin@chalmers.se>, Dag Wästberg <dwastberg@gmail.com>, George Spaias <gspaiasa@ece.auth.gr>, Jens Olsson <jens.olsson@chalmersindustriteknik.se>
Classifier: Intended Audience :: Science/Research
Classifier: Programming Language :: Python :: 3
Classifier: License :: OSI Approved :: MIT License
Requires-Python: >=3.10
License-File: LICENSE
Requires-Dist: protobuf <3.21.0,>=3.20.0
Requires-Dist: numpy
Requires-Dist: shapely
Requires-Dist: affine
Provides-Extra: test
Requires-Dist: pytest ; extra == 'test'
